{ " com ": " c/",
" de ": " d ",
" enquanto ": " enqto ",
" estou ": " tô ",
" está ": " tá ",
" estão ": " tão ",
" mais ": "+ ",
" muitas ": " mtas ",
" muito ": " mto ",
" para ": " p/",
" pouco ": " pco ",
" pra ": " p/",
" quando ": " qdo ",
" quanto ": " qto ",
" que ": " q ",
" sem ": " s/",
" tempo ": " tmp ",
" todo ": " td ",
" tudo ": " td ",
" um ": " 1 ",
" uns ": " 1s ",
" você ": " vc ",
"não": "ñ",
"Com ": "C/",
"De ": "D ",
"Enquanto ": "Enqto ",
"Estou ": "Tô ",
"Está ": "Tá ",
"Estão ": "Tão ",
"Mais ": "+ ",
"Muitas ": "Mtas ",
"Muito ": "Mto ",
"Para ": "P/",
"Pouco ": "Pco ",
"Pra ": "P/",
"Quando ": "Qdo ",
"Quanto ": "Qto ",
"Que ": "Q ",
"Sem ": "S/",
"Tempo ": "Tmp ",
"Todo ": "Td ",
"Tudo ": "Td ",
"Um ": "1 ",
"Uns ": "1s ",
"Você ": "Vc ",
"Não": "Ñ",
", ": ",",
" (": "(",
") ": ")",
": ": ":",
"! ": "!",
"? ": "?" }